pythondatautil/__init__.py
pythondatautil/datautil.py
pythondatautil/tableutil.py
pythondatautil-0.0.17.dist-info/LICENSE
pythondatautil-0.0.17.dist-info/METADATA
pythondatautil-0.0.17.dist-info/WHEEL
pythondatautil-0.0.17.dist-info/top_level.txt
pythondatautil-0.0.17.dist-info/RECORD
