Metadata-Version: 2.1
Name: pythondatautil
Version: 0.0.17
Summary: Libraries to simplify file processing in Python
Author-email: Ippei Morita <ippei0923@gmail.com>
Project-URL: Homepage, https://github.com/m-ippei/pythondatautil
Project-URL: Documentation, https://m-ippei.github.io/pythondatautil
Classifier: Programming Language :: Python :: 3
Classifier: License :: OSI Approved :: MIT License
Classifier: Operating System :: OS Independent
Requires-Python: >=3.9
License-File: LICENSE
